pyrulefilter/__init__.py
pyrulefilter/_version.py
pyrulefilter/categories.csv
pyrulefilter/enums.py
pyrulefilter/operators.py
pyrulefilter/schemas.py
pyrulefilter-0.5.0.dist-info/METADATA
pyrulefilter-0.5.0.dist-info/WHEEL
pyrulefilter-0.5.0.dist-info/licenses/licenses/BSD-3-Clause.txt
pyrulefilter-0.5.0.dist-info/RECORD
